weibull/__init__.py
weibull/version.py
weibull/weibull.py
weibull-0.1.3.dist-info/METADATA
weibull-0.1.3.dist-info/WHEEL
weibull-0.1.3.dist-info/license.txt
weibull-0.1.3.dist-info/top_level.txt
weibull-0.1.3.dist-info/zip-safe
weibull-0.1.3.dist-info/RECORD
