Metadata-Version: 2.1
Name: weibull
Version: 0.1.3
Summary: Weibull analysis and test design for reliability and life applications
Home-page: https://github.com/slightlynybbled/weibull
Author: Jason R. Jones
Author-email: slightlynybbled@gmail.com
License: MIT
Keywords: weibull reliability
Platform: UNKNOWN
Classifier: Development Status :: 3 - Alpha
Classifier: Programming Language :: Python :: 3
Classifier: Programming Language :: Python :: 3.5
Classifier: Programming Language :: Python :: 3.6
Classifier: Natural Language :: English
Requires-Dist: pandas (>=0.20.0)
Requires-Dist: matplotlib (>=2.0)
Requires-Dist: numpy (>=1.0)
Requires-Dist: scipy (>=1.0.0)
